datalogging/__init__.py
datalogging/api.py
datalogging/app_meta.py
datalogging/dbrouters.py
datalogging/enums.py
datalogging/helpers.py
datalogging/managers.py
datalogging/middleware.py
datalogging/models.py
datalogging/signals.py
datalogging/management/__init__.py
datalogging/management/commands/__init__.py
datalogging/management/commands/datalogging_compress.py
datalogging/management/commands/datalogging_partition_prepare.py
datalogging/migrations/0001_initial.py
datalogging/migrations/__init__.py
datalogging/south_migrate/__init__.py
datalogging/south_migrate/management/__init__.py
datalogging/south_migrate/management/commands/__init__.py
datalogging/south_migrate/management/commands/_migrate.py
datalogging/south_migrations/0001_initial.py
datalogging/south_migrations/0002_add_index.py
datalogging/south_migrations/0003_index_correction.py
datalogging/south_migrations/0004_drop_index.py
datalogging/south_migrations/__init__.py
datalogging/tests/__init__.py
datalogging/tests/log_table_conversion.py
m3_datalogging-2.0.3.17.dist-info/licenses/AUTHORS.txt
m3_datalogging-2.0.3.17.dist-info/licenses/LICENSE.txt
m3_datalogging-2.0.3.17.dist-info/METADATA
m3_datalogging-2.0.3.17.dist-info/WHEEL
m3_datalogging-2.0.3.17.dist-info/top_level.txt
m3_datalogging-2.0.3.17.dist-info/RECORD
