Metadata-Version: 2.4
Name: m3-datalogging
Version: 2.0.3.17
Summary: Logging system to spy on users.
Home-page: https://bitbucket.org/barsgroup/data-logging
Author: Andrew Torsunov, Kirill Borisov
Author-email: torsunov@bars-open.ru, borisov@bars-open.ru
License: MIT
Classifier: Intended Audience :: Developers
Classifier: Environment :: Web Environment
Classifier: Natural Language :: Russian
Classifier: Natural Language :: English
Classifier: Operating System :: OS Independent
Classifier: Programming Language :: Python
Classifier: License :: OSI Approved :: MIT License
Classifier: Development Status :: 5 - Production/Stable
License-File: LICENSE.txt
License-File: AUTHORS.txt
Requires-Dist: django-json-field>=0.5.8
Requires-Dist: m3_legacy>=2.1.1
Requires-Dist: architect==0.6.0
Dynamic: author
Dynamic: author-email
Dynamic: classifier
Dynamic: home-page
Dynamic: license
Dynamic: license-file
Dynamic: requires-dist
Dynamic: summary
